MANIFEST.in
README.txt
license.txt
setup.py
Django_HardWorker.egg-info/PKG-INFO
Django_HardWorker.egg-info/SOURCES.txt
Django_HardWorker.egg-info/dependency_links.txt
Django_HardWorker.egg-info/not-zip-safe
Django_HardWorker.egg-info/requires.txt
Django_HardWorker.egg-info/top_level.txt
hardworker/__init__.py
hardworker/admin.py
hardworker/decorators.py
hardworker/models.py
hardworker/tests.py
hardworker/urls.py
hardworker/views.py
hardworker/management/__init__.py
hardworker/management/commands/__init__.py
hardworker/management/commands/hardworkerdaemon.py
hardworker/middleware/__init__.py
hardworker/templatetags/__init__.py