Metadata-Version: 1.0
Name: Django-HardWorker
Version: 0.1.0
Summary: Simplified background worker for django.
Home-page: https://bitbucket.org/weholt/django-hardworker
Author: Thomas Weholt
Author-email: thomas@weholt.org
License: Modified BSD
Keywords: django background worker
Platform: UNKNOWN
Classifier: Development Status :: 4 - Beta
Classifier: Intended Audience :: Developers
Classifier: Framework :: Django
Classifier: License :: OSI Approved :: BSD License
Classifier: Operating System :: OS Independent
Classifier: Programming Language :: Python
Classifier: Topic :: Database
